pycask/__init__.py
pycask/db.py
pycask/entry.py
pycask/file.py
pycask/key_dir.py
pycask-0.5.0.dist-info/LICENSE
pycask-0.5.0.dist-info/WHEEL
pycask-0.5.0.dist-info/METADATA
pycask-0.5.0.dist-info/RECORD
