Metadata-Version: 2.1
Name: pycask
Version: 0.5.0
Summary: A Log-Structured KV Store based on bitcask, written in Python.
Home-page: https://github.com/Huangkai1008/pycask
License: MIT
Author: huangkai
Author-email: h1770360848@outlook.com
Maintainer: huangkai
Maintainer-email: h1770360848@outlook.com
Requires-Python: >=3.9,<4.0
Classifier: Development Status :: 4 - Beta
Classifier: License :: OSI Approved :: MIT License
Classifier: Operating System :: OS Independent
Classifier: Programming Language :: Python :: 3
Classifier: Programming Language :: Python :: 3.10
Classifier: Programming Language :: Python :: 3.9
Classifier: Topic :: Database
Project-URL: Repository, https://github.com/Huangkai1008/pycask
